{
    "annotations": {
        "list": [
            {
                "builtIn": 1,
                "datasource": {
                    "type": "grafana",
                    "uid": "-- Grafana --"
                },
                "enable": true,
                "hide": true,
                "iconColor": "rgba(0, 211, 255, 1)",
                "name": "Annotations & Alerts",
                "type": "dashboard"
            }
        ]
    },
    "description": "Visualizes Taiga sprint metrics — velocity, story points per sprint, and sprint duration analysis.",
    "editable": true,
    "fiscalYearStartMonth": 0,
    "graphTooltip": 1,
    "id": null,
    "links": [],
    "panels": [
        {
            "datasource": {
                "type": "grafana-postgresql-datasource",
                "uid": "postgres-metrics"
            },
            "description": "Total velocity (completed story points) from the most recent sprint.",
            "fieldConfig": {
                "defaults": {
                    "color": {
                        "mode": "thresholds"
                    },
                    "decimals": 0,
                    "mappings": [],
                    "thresholds": {
                        "mode": "absolute",
                        "steps": [
                            {
                                "color": "red",
                                "value": 0
                            },
                            {
                                "color": "yellow",
                                "value": 10
                            },
                            {
                                "color": "green",
                                "value": 20
                            }
                        ]
                    }
                },
                "overrides": []
            },
            "gridPos": {
                "h": 4,
                "w": 8,
                "x": 0,
                "y": 0
            },
            "id": 1,
            "options": {
                "colorMode": "value",
                "graphMode": "area",
                "justifyMode": "auto",
                "orientation": "auto",
                "reduceOptions": {
                    "calcs": [
                        "lastNotNull"
                    ],
                    "fields": "",
                    "values": false
                },
                "textMode": "auto",
                "wideLayout": true
            },
            "pluginVersion": "12.3.2",
            "targets": [
                {
                    "datasource": {
                        "type": "postgres",
                        "uid": "postgres-metrics"
                    },
                    "editorMode": "code",
                    "format": "table",
                    "rawQuery": true,
                    "rawSql": "SELECT total_velocity AS \"Sprint Velocity\"\nFROM \"Focus Factor\"\nORDER BY created_at DESC\nLIMIT 1;",
                    "refId": "A"
                }
            ],
            "title": "Latest Sprint Velocity",
            "type": "stat"
        },
        {
            "datasource": {
                "type": "grafana-postgresql-datasource",
                "uid": "postgres-metrics"
            },
            "description": "Average story points per sprint day from the most recent sprint.",
            "fieldConfig": {
                "defaults": {
                    "color": {
                        "mode": "thresholds"
                    },
                    "decimals": 2,
                    "mappings": [],
                    "thresholds": {
                        "mode": "absolute",
                        "steps": [
                            {
                                "color": "green",
                                "value": 0
                            },
                            {
                                "color": "yellow",
                                "value": 5
                            },
                            {
                                "color": "red",
                                "value": 10
                            }
                        ]
                    }
                },
                "overrides": []
            },
            "gridPos": {
                "h": 4,
                "w": 8,
                "x": 8,
                "y": 0
            },
            "id": 2,
            "options": {
                "colorMode": "value",
                "graphMode": "none",
                "justifyMode": "auto",
                "orientation": "auto",
                "reduceOptions": {
                    "calcs": [
                        "lastNotNull"
                    ],
                    "fields": "",
                    "values": false
                },
                "textMode": "auto",
                "wideLayout": true
            },
            "pluginVersion": "12.3.2",
            "targets": [
                {
                    "datasource": {
                        "type": "postgres",
                        "uid": "postgres-metrics"
                    },
                    "editorMode": "code",
                    "format": "table",
                    "rawQuery": true,
                    "rawSql": "SELECT ROUND(\n  CASE WHEN days_list = 0 THEN 0\n       ELSE storypoints::numeric / days_list\n  END, 2\n) AS \"Avg Story Points / Day\"\nFROM \"AUC\"\nORDER BY created_at DESC\nLIMIT 1;",
                    "refId": "A"
                }
            ],
            "title": "Avg Story Points per Sprint Day",
            "type": "stat"
        },
        {
            "datasource": {
                "type": "grafana-postgresql-datasource",
                "uid": "postgres-metrics"
            },
            "description": "Sprint duration in days from the latest AUC record.",
            "fieldConfig": {
                "defaults": {
                    "color": {
                        "fixedColor": "purple",
                        "mode": "fixed"
                    },
                    "mappings": [],
                    "thresholds": {
                        "mode": "absolute",
                        "steps": [
                            {
                                "color": "purple",
                                "value": 0
                            }
                        ]
                    }
                },
                "overrides": []
            },
            "gridPos": {
                "h": 4,
                "w": 8,
                "x": 16,
                "y": 0
            },
            "id": 3,
            "options": {
                "colorMode": "value",
                "graphMode": "none",
                "justifyMode": "auto",
                "orientation": "auto",
                "reduceOptions": {
                    "calcs": [
                        "lastNotNull"
                    ],
                    "fields": "",
                    "values": false
                },
                "textMode": "auto",
                "wideLayout": true
            },
            "pluginVersion": "12.3.2",
            "targets": [
                {
                    "datasource": {
                        "type": "postgres",
                        "uid": "postgres-metrics"
                    },
                    "editorMode": "code",
                    "format": "table",
                    "rawQuery": true,
                    "rawSql": "SELECT days_list AS \"Sprint Duration (days)\"\nFROM \"AUC\"\nORDER BY created_at DESC\nLIMIT 1;",
                    "refId": "A"
                }
            ],
            "title": "Sprint Duration (days)",
            "type": "stat"
        },
        {
            "datasource": {
                "type": "grafana-postgresql-datasource",
                "uid": "postgres-metrics"
            },
            "description": "Velocity trend across all recorded sprints from Focus Factor table.",
            "fieldConfig": {
                "defaults": {
                    "color": {
                        "mode": "palette-classic"
                    },
                    "custom": {
                        "axisBorderShow": false,
                        "axisColorMode": "text",
                        "axisLabel": "Velocity (completed pts)",
                        "axisPlacement": "auto",
                        "drawStyle": "line",
                        "fillOpacity": 15,
                        "gradientMode": "none",
                        "lineInterpolation": "linear",
                        "lineWidth": 2,
                        "pointSize": 6,
                        "showPoints": "always",
                        "spanNulls": false
                    },
                    "mappings": [],
                    "thresholds": {
                        "mode": "absolute",
                        "steps": [
                            {
                                "color": "green",
                                "value": 0
                            },
                            {
                                "color": "red",
                                "value": 80
                            }
                        ]
                    }
                },
                "overrides": []
            },
            "gridPos": {
                "h": 10,
                "w": 12,
                "x": 0,
                "y": 4
            },
            "id": 4,
            "options": {
                "legend": {
                    "calcs": [
                        "mean",
                        "max"
                    ],
                    "displayMode": "list",
                    "placement": "bottom",
                    "showLegend": true
                },
                "tooltip": {
                    "hideZeros": false,
                    "mode": "single",
                    "sort": "none"
                }
            },
            "pluginVersion": "12.3.2",
            "targets": [
                {
                    "datasource": {
                        "type": "postgres",
                        "uid": "postgres-metrics"
                    },
                    "editorMode": "code",
                    "format": "time_series",
                    "rawQuery": true,
                    "rawSql": "SELECT created_at    AS \"time\",\n       total_velocity AS \"Sprint Velocity\"\nFROM \"Focus Factor\"\nORDER BY created_at ASC;",
                    "refId": "A"
                }
            ],
            "title": "Sprint Velocity Trend",
            "type": "timeseries"
        },
        {
            "datasource": {
                "type": "grafana-postgresql-datasource",
                "uid": "postgres-metrics"
            },
            "description": "Total story points and sprint duration across all sprints. Shows whether longer sprints produce more points.",
            "fieldConfig": {
                "defaults": {
                    "color": {
                        "mode": "palette-classic"
                    },
                    "custom": {
                        "axisBorderShow": false,
                        "axisColorMode": "text",
                        "axisLabel": "Count",
                        "axisPlacement": "auto",
                        "drawStyle": "line",
                        "fillOpacity": 10,
                        "gradientMode": "none",
                        "lineInterpolation": "smooth",
                        "lineWidth": 2,
                        "pointSize": 5,
                        "showPoints": "always",
                        "spanNulls": false
                    },
                    "mappings": [],
                    "thresholds": {
                        "mode": "absolute",
                        "steps": [
                            {
                                "color": "green",
                                "value": 0
                            }
                        ]
                    }
                },
                "overrides": []
            },
            "gridPos": {
                "h": 10,
                "w": 12,
                "x": 12,
                "y": 4
            },
            "id": 5,
            "options": {
                "legend": {
                    "calcs": [
                        "mean"
                    ],
                    "displayMode": "list",
                    "placement": "bottom",
                    "showLegend": true
                },
                "tooltip": {
                    "hideZeros": false,
                    "mode": "multi",
                    "sort": "none"
                }
            },
            "pluginVersion": "12.3.2",
            "targets": [
                {
                    "datasource": {
                        "type": "postgres",
                        "uid": "postgres-metrics"
                    },
                    "editorMode": "code",
                    "format": "time_series",
                    "rawQuery": true,
                    "rawSql": "SELECT created_at  AS \"time\",\n       storypoints AS \"Total Story Points\",\n       days_list   AS \"Sprint Duration (days)\"\nFROM \"AUC\"\nORDER BY created_at ASC;",
                    "refId": "A"
                }
            ],
            "title": "Story Points vs Sprint Duration",
            "type": "timeseries"
        },
        {
            "datasource": {
                "type": "grafana-postgresql-datasource",
                "uid": "postgres-metrics"
            },
            "description": "Full sprint history joining Focus Factor and AUC tables on run_id.",
            "fieldConfig": {
                "defaults": {
                    "color": {
                        "mode": "thresholds"
                    },
                    "custom": {
                        "align": "auto",
                        "cellOptions": {
                            "type": "auto"
                        },
                        "inspect": false
                    },
                    "mappings": [],
                    "thresholds": {
                        "mode": "absolute",
                        "steps": [
                            {
                                "color": "green",
                                "value": 0
                            }
                        ]
                    }
                },
                "overrides": [
                    {
                        "matcher": {
                            "id": "byName",
                            "options": "Velocity"
                        },
                        "properties": [
                            {
                                "id": "custom.cellOptions",
                                "value": {
                                    "mode": "gradient",
                                    "type": "gauge"
                                }
                            },
                            {
                                "id": "min",
                                "value": 0
                            },
                            {
                                "id": "max",
                                "value": 50
                            }
                        ]
                    },
                    {
                        "matcher": {
                            "id": "byName",
                            "options": "Avg Pts/Day"
                        },
                        "properties": [
                            {
                                "id": "custom.cellOptions",
                                "value": {
                                    "mode": "gradient",
                                    "type": "gauge"
                                }
                            },
                            {
                                "id": "min",
                                "value": 0
                            },
                            {
                                "id": "max",
                                "value": 10
                            }
                        ]
                    }
                ]
            },
            "gridPos": {
                "h": 10,
                "w": 24,
                "x": 0,
                "y": 14
            },
            "id": 6,
            "options": {
                "cellHeight": "sm",
                "showHeader": true,
                "sortBy": [
                    {
                        "desc": true,
                        "displayName": "Recorded At"
                    }
                ]
            },
            "pluginVersion": "12.3.2",
            "targets": [
                {
                    "datasource": {
                        "type": "postgres",
                        "uid": "postgres-metrics"
                    },
                    "editorMode": "code",
                    "format": "table",
                    "rawQuery": true,
                    "rawSql": "SELECT\n  ff.created_at                                         AS \"Recorded At\",\n  ff.total_velocity                                     AS \"Velocity\",\n  ff.total_story_points                                 AS \"Total Story Points\",\n  a.days_list                                           AS \"Sprint Duration (days)\",\n  ROUND(\n    CASE WHEN a.days_list = 0 THEN 0\n         ELSE a.storypoints::numeric / a.days_list\n    END, 2\n  )                                                     AS \"Avg Pts/Day\",\n  a.business_value                                      AS \"Business Value\"\nFROM \"Focus Factor\" ff\nJOIN \"AUC\" a ON ff.run_id = a.run_id\nORDER BY ff.created_at DESC;",
                    "refId": "A"
                }
            ],
            "title": "Sprint Summary Table (Velocity / Story Points / Duration)",
            "type": "table"
        }
    ],
    "preload": false,
    "refresh": "30s",
    "schemaVersion": 42,
    "tags": [
        "taiga",
        "sprint",
        "velocity",
        "metrics",
        "sprint-review"
    ],
    "templating": {
        "list": []
    },
    "timepicker": {},
    "timezone": "browser",
    "title": "Taiga Sprint Metrics Dashboard",
    "uid": "taiga-sprint-metrics",
    "version": 1
}